mcp_dify_knowledge/__init__.py
mcp_dify_knowledge/__main__.py
mcp_dify_knowledge-0.1.1.dist-info/METADATA
mcp_dify_knowledge-0.1.1.dist-info/WHEEL
mcp_dify_knowledge-0.1.1.dist-info/entry_points.txt
mcp_dify_knowledge-0.1.1.dist-info/RECORD
